<?xml version="1.0" encoding="UTF-8"?>
<nsjusecase xmlns:xsi="http://www.w3.org/2001/XMLSchema-instance" xsi:noNamespaceSchemaLocation="../../vendor/nasajon/mdatransformer/schemas/nsjusecase.xsd" project="ns/pessoas" name="logos" label="logos">
    <entity schema="ns" table="pessoaslogos">
        <fieldmodel name="pessoalogo" datatype="guid" isid="true" column="pessoalogo" />
        <fieldmodel name="idpessoa" datatype="guid" column="id_pessoa" />
        <fieldmodel name="pathlogo" datatype="string" column="path_logo" />
        <fieldmodel name="ativo" datatype="boolean" column="ativo" />
        <fieldmodel name="created_at" datatype="date" column="created_at" />
        <fieldmodel name="created_by" datatype="json" column="created_by" />
        <fieldmodel name="updated_at" datatype="date" column="updated_at" />
        <fieldmodel name="updated_by" datatype="json" column="updated_by" />
        <!-- Nesse campo será enviado a imagem da logo -->
        <fieldmodel name="logo" datatype="string" notMapped="true" />
        <fieldmodel name="id_grupoempresarial" datatype="guid" column="id_grupoempresarial" />
        <fieldmodel name="tenant" datatype="integer" column="tenant" />
    </entity>
    <constructors>
        <constructoritem required="true">idpessoa</constructoritem>
        <constructoritem required="true">tenant</constructoritem>
    </constructors>
    <viewbrowser paginate="true" layout="table" target="builtin" label="Logos do fornecedor">
        <fieldsbrowser>
            <fieldbrowser alias="pessoalogo" entitylink="pessoalogo" visible="false" />
            <fieldbrowser alias="idpessoa" entitylink="idpessoa" visible="false" />  
            <fieldbrowser alias="pathlogo" entitylink="pathlogo" visible="false" />            
            <fieldbrowser alias="ativo" entitylink="ativo" visible="false" />
            <fieldbrowser alias="id_grupoempresarial" entitylink="id_grupoempresarial" visible="false" />
            <fieldbrowser alias="tenant" entitylink="tenant" visible="false" />
        </fieldsbrowser>
    </viewbrowser>
    <forms>
        <form name="default">
            <layout>
                <headerform>
                    <row>
                        <cell name="idpessoa" controltype="hidden" label="Nome" colspan="2" entitylink="idpessoa">
                        </cell>
                        <cell name="pathlogo" controltype="hidden" label="Nome" colspan="2" entitylink="pathlogo">
                        </cell>
                    </row>
                </headerform>
            </layout>
        </form>
    </forms>
    <actions>
        <action>
            <name>Insert</name>
            <api>
                <name>atualizapessoalogo</name>
                <fromto valueapi="idpessoa" valueentity ="idpessoa" />
                <fromto valueapi="id_grupoempresarial" valueentity="id_grupoempresarial" />
                <fromto valueapi="tenant" valueentity="tenant" />
                <fromto valueapi="pathlogo" valueentity="pathlogo" />
                <fromto valueapi="created_by" valueentity="logged_user" />
            </api>
        </action>
    </actions>
</nsjusecase>